retarus/commons/config.py
retarus/commons/exceptions.py
retarus/commons/region.py
retarus/commons/transport.py
retarus/commons/utils.py
retarus_common-0.1.3.dist-info/LICENSE
retarus_common-0.1.3.dist-info/METADATA
retarus_common-0.1.3.dist-info/WHEEL
retarus_common-0.1.3.dist-info/top_level.txt
retarus_common-0.1.3.dist-info/RECORD
