Metadata-Version: 2.1
Name: retarus-common
Version: 0.1.3
Author-email: Retarus GmbH <Developers@retarus.com>
License: Apache License
Project-URL: repository, https://github.com/retarus/retarus-python
Requires-Python: >=3.8
License-File: LICENSE
Requires-Dist: wheel
Requires-Dist: pytest
Requires-Dist: aiohttp
Requires-Dist: aiohttp-retry
Requires-Dist: pydantic
Requires-Dist: pytest-asyncio
Requires-Dist: requests
Requires-Dist: dataclasses
